libqcanvas_clients/__init__.py
libqcanvas_clients/canvas/__init__.py
libqcanvas_clients/canvas/canvas_authenticator.py
libqcanvas_clients/canvas/canvas_client.py
libqcanvas_clients/canvas/canvas_client_config.py
libqcanvas_clients/canvas/canvas_types.py
libqcanvas_clients/canvas/canvas_unauthenticated_detector_hook.py
libqcanvas_clients/panopto/__init__.py
libqcanvas_clients/panopto/fake_panopto_client.py
libqcanvas_clients/panopto/panopto_authenticator.py
libqcanvas_clients/panopto/panopto_client.py
libqcanvas_clients/panopto/panopto_client_config.py
libqcanvas_clients/panopto/panopto_types.py
libqcanvas_clients/panopto/panopto_unauthenticated_detector_hook.py
libqcanvas_clients/util/__init__.py
libqcanvas_clients/util/add_cookies_to_request_hook.py
libqcanvas_clients/util/authenticator.py
libqcanvas_clients/util/external_client_httpx_transport.py
libqcanvas_clients/util/json_util.py
libqcanvas_clients/util/request_exceptions.py
libqcanvas_clients/util/url_converter.py
libqcanvas_clients-2026.1.20.dist-info/METADATA
libqcanvas_clients-2026.1.20.dist-info/WHEEL
libqcanvas_clients-2026.1.20.dist-info/RECORD
